puml_viewer/__init__.py
puml_viewer/__main__.py
puml_viewer/templates/index.html
puml_viewer-1.0.20.dist-info/entry_points.txt
puml_viewer-1.0.20.dist-info/LICENSE
puml_viewer-1.0.20.dist-info/WHEEL
puml_viewer-1.0.20.dist-info/METADATA
puml_viewer-1.0.20.dist-info/RECORD
